LICENSE
MANIFEST.in
README.rst
setup.cfg
setup.py
smeterd_exporter/__init__.py
smeterd_exporter.egg-info/PKG-INFO
smeterd_exporter.egg-info/SOURCES.txt
smeterd_exporter.egg-info/dependency_links.txt
smeterd_exporter.egg-info/entry_points.txt
smeterd_exporter.egg-info/not-zip-safe
smeterd_exporter.egg-info/requires.txt
smeterd_exporter.egg-info/top_level.txt