Metadata-Version: 1.1
Name: smeterd-exporter
Version: 0.9.2
Summary: A prometheus exporter for you smart meter.
Home-page: https://github.com/nrocco/smeterd_exporter
Author: Nico Di Rocco
Author-email: dirocco.nico@gmail.com
License: GPLv3
Download-URL: https://github.com/nrocco/smeterd_exporter
Platform: UNKNOWN
Classifier: Development Status :: 5 - Production/Stable
Classifier: Environment :: Console
Classifier: License :: OSI Approved :: GNU General Public License v3 (GPLv3)
Classifier: Operating System :: Unix
Classifier: Programming Language :: Python
Classifier: Programming Language :: Python :: 2
Classifier: Programming Language :: Python :: 2.7
Classifier: Programming Language :: Python :: 3
Classifier: Programming Language :: Python :: 3.2
Classifier: Programming Language :: Python :: 3.3
Classifier: Programming Language :: Python :: 3.4
Classifier: Programming Language :: Python :: 3.5
Classifier: Topic :: Software Development :: Libraries :: Python Modules
Classifier: Topic :: Utilities
